MANIFEST.in
README.rst
setup.cfg
setup.py
tw2/__init__.py
tw2.jqplugins.portlets.egg-info/PKG-INFO
tw2.jqplugins.portlets.egg-info/SOURCES.txt
tw2.jqplugins.portlets.egg-info/dependency_links.txt
tw2.jqplugins.portlets.egg-info/entry_points.txt
tw2.jqplugins.portlets.egg-info/namespace_packages.txt
tw2.jqplugins.portlets.egg-info/not-zip-safe
tw2.jqplugins.portlets.egg-info/requires.txt
tw2.jqplugins.portlets.egg-info/top_level.txt
tw2/jqplugins/__init__.py
tw2/jqplugins/portlets/__init__.py
tw2/jqplugins/portlets/base.py
tw2/jqplugins/portlets/defaults.py
tw2/jqplugins/portlets/samples.py
tw2/jqplugins/portlets/widgets.py
tw2/jqplugins/portlets/static/jquery/portlets/css/portlets.css
tw2/jqplugins/portlets/static/jquery/portlets/js/portlets.js
tw2/jqplugins/portlets/templates/__init__.py
tw2/jqplugins/portlets/templates/__init__.pyc
tw2/jqplugins/portlets/templates/column.mak
tw2/jqplugins/portlets/templates/layout.mak
tw2/jqplugins/portlets/templates/portlet.mak